{
  "id": "pucchnumber",
  "name": "PUCCH Number",
  "records": [
    {
      "id": "0xb8d2-nr5g-ll1-fw-mac-tx-iu-power",
      "logcode": "0xB8D2",
      "title": "0xB8D2 NR5G LL1 FW MAC TX IU Power",
      "name": "NR5G LL1 FW MAC TX IU Power",
      "category": "ML1",
      "dataFile": "0xB8D2__NR5G_LL1_FW_MAC_TX_IU_Power.json",
      "paths": [
        "NR5G LL1 FW MAC TX IU Power -> Sub Packets -> [] -> TX IU Power Sub Packet -> SubVersion -> Power Info -> [] -> PUCCH Data -> PUCCH Number"
      ]
    }
  ]
}
